{
    "format_version": "1.18",
    "minecraft:block": {
        "description": {
            "identifier": "bright:purple_light_fixture",
            "properties": {
                "bright:facing": [
                    0,
                    1,
                    2,
                    3,
                    4,
                    5,
                    6
                ],
                "bright:lit": [
                    false,
                    true
                ]
            }
        },
        "components": {
            "minecraft:loot": "loot_tables/blocks/purple_light_fixture.json",
            "tag:non_solid": {},
            "minecraft:block_light_filter": 0,
            "minecraft:destroy_time": 0.3,
            "minecraft:explosion_resistance": 0.3,
            "minecraft:geometry": "geometry.light_fixture",
            "minecraft:block_collision": {
                "origin": [
                    -2,
                    10,
                    5
                ],
                "size": [
                    4,
                    5,
                    3
                ]
            },
            "minecraft:aim_collision": {
                "origin": [
                    -2,
                    10,
                    5
                ],
                "size": [
                    4,
                    5,
                    3
                ]
            },
            "minecraft:creative_category": {
                "category": "items",
                "group": "itemGroup.search"
            },
            "minecraft:on_player_placing": {
                "event": "bright:facing"
            },
            "minecraft:placement_filter": {
                "conditions": [
                    {
                        "allowed_faces": [
                            "side"
                        ],
                        "block_filter": [
                            {
                                "tags": "!q.any_tag('non_solid')"
                            }
                        ]
                    }
                ]
            }
        },
        "permutations": [
            {
                "condition": "q.block_property('bright:facing') == 0 || q.block_property('bright:facing') == 1 || q.block_property('bright:facing') == 2",
                "components": {
                    "minecraft:rotation": [
                        0,
                        0,
                        0
                    ]
                }
            },
            {
                "condition": "q.block_property('bright:facing') == 3",
                "components": {
                    "minecraft:rotation": [
                        0,
                        180,
                        0
                    ]
                }
            },
            {
                "condition": "q.block_property('bright:facing') == 4",
                "components": {
                    "minecraft:rotation": [
                        0,
                        90,
                        0
                    ]
                }
            },
            {
                "condition": "q.block_property('bright:facing') == 5",
                "components": {
                    "minecraft:rotation": [
                        0,
                        -90,
                        0
                    ]
                }
            },
            {
                "condition": "q.block_property('bright:lit') == true",
                "components": {
                    "minecraft:block_light_emission": 0.5,
                    "minecraft:material_instances": {
                        "*": {
                            "texture": "minecraft:purple_concrete"
                        },
                        "base": {
                            "texture": "minecraft:purple_concrete"
                        },
                        "light": {
                            "texture": "bright:purple_light_lit"
                        }
                    },
                    "minecraft:on_interact": {
                        "event": "bright:lit_false"
                    }
                }
            },
            {
                "condition": "q.block_property('bright:lit') == false",
                "components": {
                    "minecraft:material_instances": {
                        "*": {
                            "texture": "minecraft:purple_concrete"
                        },
                        "base": {
                            "texture": "minecraft:purple_concrete"
                        },
                        "light": {
                            "texture": "bright:purple_light"
                        }
                    },
                    "minecraft:on_interact": {
                        "event": "bright:lit_true"
                    }
                }
            }
        ],
        "events": {
            "bright:lit_true": {
                "set_block_property": {
                    "bright:lit": "true"
                },
                "run_command": {
                    "command": "playsound random.click @p ~ ~ ~ 0.5"
                }
            },
            "bright:lit_false": {
                "set_block_property": {
                    "bright:lit": "false"
                },
                "run_command": {
                    "command": "playsound random.click @p ~ ~ ~ 0.5"
                }
            },
            "bright:facing": {
                "set_block_property": {
                    "bright:facing": "q.cardinal_block_face_placed_on"
                }
            }
        }
    }
}