{
    "format_version": "1.17.1",
    "minecraft:recipe_shaped": {
        "description": {
            "identifier": "const:green_crafting_table"
        },
        "tags": [
            "crafting_table"
        ],
        "group": "crafting_table",
        "pattern": [
            "##",
            "##"
        ],
        "key": {
            "#": {
                "item": "const:green_planks"
            }
        },
        "result": {
            "item": "const:green_crafting_table"
        }
    }
}