{
  "format_version": "1.21.10",
  "minecraft:recipe_shaped": {
    "description": {
      "identifier": "magnet:iron_magnet"
    },
    "tags": ["crafting_table"],
    "pattern": ["B R", "I I", "III"],
    "key": {
      "B": {
        "item": "minecraft:blue_dye"
      },
      "R": {
        "item": "minecraft:red_dye"
      },
      "I": {
        "item": "minecraft:iron_ingot"
      }
    },
    "result": "magnet:iron_magnet",
    "unlock": [
      {
        "item": "minecraft:blue_dye"
      },
      {
        "item": "minecraft:red_dye"
      },
      {
        "item": "minecraft:iron_ingot"
      }
    ]
  }
}
